{
    "type": "minecraft:crafting_shaped",
    "pattern": [
        " WF",
        "PEB",
        " W "
    ],
    "key": {
        "W": {
            "item": "biomesoplenty:palm_slab"
        },
        "F": {
            "item": "minecraft:furnace"
        },
        "B": {
            "item": "biomesoplenty:palm_boat"
        },
        "E": {
            "item": "simpleplanes:furnace_engine"
        },
        "P": {
            "item": "simpleplanes:propeller"
        }
    },
    "result": {
        "item": "simpleplanes:bop_palm_plane"
    }
}
